[{"city": "Tampa", "state": "FL", "surname": "Baker", "firstName": "Kathryn", "address": "434 View Ct.", "zipCode": "32251", "phone": "(957) 558 - 7746", "email": "kathryn.baker@example.com"}, {"city": "Miami", "state": "FL", "surname": "Powell", "firstName": "Tammy", "address": "234 Cedar Cir.", "zipCode": "32497", "phone": "(312) 812 - 9215", "email": "tammy.powell@example.com"}, {"city": "Jacksonville", "state": "FL", "surname": "Butler", "firstName": "Edward", "address": "102 Washington Ave.", "zipCode": "32284", "phone": "(972) 732 - 6111", "email": "edward.butler@example.com"}, {"city": "Orlando", "state": "FL", "surname": "Cox", "firstName": "Gloria", "address": "612 Fifth Ct.", "zipCode": "32255", "phone": "(915) 336 - 5673", "email": "gloria.cox@example.com"}, {"city": "Tampa", "state": "FL", "surname": "Sanders", "firstName": "Jeremy", "address": "167 Main St.", "zipCode": "32165", "phone": "(562) 192 - 5152", "email": "jeremy.sanders@example.com"}, {"city": "Miami", "state": "FL", "surname": "Hill", "firstName": "Tyler", "address": "342 Pine St.", "zipCode": "32261", "phone": "(224) 833 - 9369", "email": "tyler.hill@example.com"}, {"city": "Miami", "state": "FL", "surname": "Adams", "firstName": "Rachel", "address": "613 View Ct.", "zipCode": "32744", "phone": "(373) 662 - 7143", "email": "rachel.adams@example.com"}, {"city": "Orlando", "state": "FL", "surname": "Griffin", "firstName": "Lauren", "address": "376 Elm Cir.", "zipCode": "32989", "phone": "(222) 328 - 3397", "email": "lauren.griffin@example.com"}, {"city": "Tallahassee", "state": "FL", "surname": "Henderson", "firstName": "Mary", "address": "738 Second Ln.", "zipCode": "32635", "phone": "(858) 591 - 1942", "email": "mary.henderson@example.com"}, {"city": "Tampa", "state": "FL", "surname": "Griffin", "firstName": "Betty", "address": "771 Lake Rd.", "zipCode": "32672", "phone": "(592) 349 - 8413", "email": "betty.griffin@example.com"}, {"city": "Orlando", "state": "FL", "surname": "Garcia", "firstName": "Zachary", "address": "28 View Cir.", "zipCode": "32548", "phone": "(597) 297 - 1641", "email": "zachary.garcia@example.com"}, {"city": "Jacksonville", "state": "FL", "surname": "Walker", "firstName": "Brandon", "address": "297 First Cir.", "zipCode": "32352", "phone": "(629) 477 - 3664", "email": "brandon.walker@example.com"}, {"city": "Orlando", "state": "FL", "surname": "Reed", "firstName": "John", "address": "840 View Ave.", "zipCode": "32249", "phone": "(462) 118 - 7882", "email": "john.reed@example.com"}, {"city": "Tampa", "state": "FL", "surname": "Flores", "firstName": "Stephanie", "address": "581 Oak Blvd.", "zipCode": "32933", "phone": "(294) 673 - 8544", "email": "stephanie.flores@example.com"}, {"city": "Jacksonville", "state": "FL", "surname": "Williams", "firstName": "Joyce", "address": "13 Eighth Rd.", "zipCode": "32728", "phone": "(697) 249 - 8778", "email": "joyce.williams@example.com"}, {"city": "Jacksonville", "state": "FL", "surname": "Foster", "firstName": "Zachary", "address": "258 Hill Cir.", "zipCode": "32744", "phone": "(976) 325 - 3448", "email": "zachary.foster@example.com"}, {"city": "Tallahassee", "state": "FL", "surname": "Bryant", "firstName": "Kyle", "address": "564 First Ave.", "zipCode": "32613", "phone": "(347) 491 - 3833", "email": "kyle.bryant@example.com"}, {"city": "Gainesville", "state": "FL", "surname": "Baker", "firstName": "Julia", "address": "262 Elm Rd.", "zipCode": "32489", "phone": "(855) 822 - 7993", "email": "julia.baker@example.com"}, {"city": "Tampa", "state": "FL", "surname": "Peterson", "firstName": "Julie", "address": "952 First St.", "zipCode": "32285", "phone": "(275) 192 - 8626", "email": "julie.peterson@example.com"}, {"city": "Miami", "state": "FL", "surname": "Miller", "firstName": "Eric", "address": "946 Fifth Cir.", "zipCode": "32622", "phone": "(764) 376 - 2666", "email": "eric.miller@example.com"}, {"city": "Tallahassee", "state": "FL", "surname": "Johnson", "firstName": "Margaret", "address": "717 Oak Rd.", "zipCode": "32786", "phone": "(417) 497 - 3651", "email": "margaret.johnson@example.com"}, {"city": "Jacksonville", "state": "FL", "surname": "Wright", "firstName": "Julie", "address": "643 Oak Rd.", "zipCode": "32144", "phone": "(255) 949 - 5485", "email": "julie.wright@example.com"}, {"city": "Tampa", "state": "FL", "surname": "Jenkins", "firstName": "Jesse", "address": "6 Third Ln.", "zipCode": "32721", "phone": "(539) 596 - 9596", "email": "jesse.jenkins@example.com"}, {"city": "Gainesville", "state": "FL", "surname": "Coleman", "firstName": "Scott", "address": "763 Hill Ct.", "zipCode": "32119", "phone": "(918) 318 - 2254", "email": "scott.coleman@example.com"}, {"city": "Miami", "state": "FL", "surname": "Wilson", "firstName": "Tammy", "address": "351 View Ave.", "zipCode": "32559", "phone": "(814) 147 - 7332", "email": "tammy.wilson@example.com"}, {"city": "Tallahassee", "state": "FL", "surname": "Bell", "firstName": "Christian", "address": "442 Ninth Blvd.", "zipCode": "32332", "phone": "(129) 759 - 5189", "email": "christian.bell@example.com"}, {"city": "Tallahassee", "state": "FL", "surname": "Perry", "firstName": "Austin", "address": "567 First St.", "zipCode": "32483", "phone": "(858) 969 - 8881", "email": "austin.perry@example.com"}, {"city": "Orlando", "state": "FL", "surname": "Green", "firstName": "Diane", "address": "969 Fifth Cir.", "zipCode": "32516", "phone": "(962) 937 - 2613", "email": "diane.green@example.com"}, {"city": "Miami", "state": "FL", "surname": "Hall", "firstName": "Jack", "address": "997 Park St.", "zipCode": "32657", "phone": "(257) 535 - 4481", "email": "jack.hall@example.com"}, {"city": "Gainesville", "state": "FL", "surname": "Murphy", "firstName": "Jane", "address": "358 Elm Cir.", "zipCode": "32277", "phone": "(699) 899 - 8685", "email": "jane.murphy@example.com"}, {"city": "Jacksonville", "state": "FL", "surname": "Russell", "firstName": "Linda", "address": "213 Lake Ln.", "zipCode": "32543", "phone": "(946) 333 - 4466", "email": "linda.russell@example.com"}, {"city": "Tampa", "state": "FL", "surname": "Lee", "firstName": "Jack", "address": "394 Maple Ln.", "zipCode": "32775", "phone": "(859) 654 - 9737", "email": "jack.lee@example.com"}, {"city": "Gainesville", "state": "FL", "surname": "Thomas", "firstName": "Gloria", "address": "9 Sixth Cir.", "zipCode": "32962", "phone": "(773) 318 - 4939", "email": "gloria.thomas@example.com"}, {"city": "Jacksonville", "state": "FL", "surname": "Young", "firstName": "Janice", "address": "997 Eighth Ln.", "zipCode": "32695", "phone": "(666) 357 - 4688", "email": "janice.young@example.com"}, {"city": "Orlando", "state": "FL", "surname": "Wood", "firstName": "Nathan", "address": "910 Third Ln.", "zipCode": "32516", "phone": "(525) 563 - 4788", "email": "nathan.wood@example.com"}, {"city": "Tallahassee", "state": "FL", "surname": "Nelson", "firstName": "Samuel", "address": "766 Cedar Blvd.", "zipCode": "32731", "phone": "(124) 955 - 7399", "email": "samuel.nelson@example.com"}, {"city": "Orlando", "state": "FL", "surname": "Richardson", "firstName": "Samuel", "address": "244 Hill St.", "zipCode": "32343", "phone": "(964) 642 - 6139", "email": "samuel.richardson@example.com"}, {"city": "Tampa", "state": "FL", "surname": "Roberts", "firstName": "Russell", "address": "227 Lake Ct.", "zipCode": "32628", "phone": "(558) 579 - 3115", "email": "russell.roberts@example.com"}, {"city": "Jacksonville", "state": "FL", "surname": "Brooks", "firstName": "Adam", "address": "241 Elm Rd.", "zipCode": "32845", "phone": "(245) 353 - 5898", "email": "adam.brooks@example.com"}, {"city": "Tallahassee", "state": "FL", "surname": "Coleman", "firstName": "Randy", "address": "914 Cedar Ln.", "zipCode": "32384", "phone": "(593) 521 - 4686", "email": "randy.coleman@example.com"}, {"city": "Tallahassee", "state": "FL", "surname": "Rogers", "firstName": "Emily", "address": "725 Lake Ln.", "zipCode": "32134", "phone": "(895) 853 - 8552", "email": "emily.rogers@example.com"}, {"city": "Miami", "state": "FL", "surname": "Anderson", "firstName": "Crystal", "address": "50 Hill Ave.", "zipCode": "32827", "phone": "(667) 717 - 2859", "email": "crystal.anderson@example.com"}, {"city": "Tallahassee", "state": "FL", "surname": "Moore", "firstName": "Amy", "address": "39 Sixth Ct.", "zipCode": "32129", "phone": "(874) 335 - 1956", "email": "amy.moore@example.com"}, {"city": "Orlando", "state": "FL", "surname": "Gonzalez", "firstName": "Louis", "address": "549 Second Ct.", "zipCode": "32872", "phone": "(317) 938 - 4448", "email": "louis.gonzalez@example.com"}, {"city": "Tallahassee", "state": "FL", "surname": "Thomas", "firstName": "Theresa", "address": "475 Oak St.", "zipCode": "32978", "phone": "(884) 677 - 8188", "email": "theresa.thomas@example.com"}, {"city": "Miami", "state": "FL", "surname": "Gonzalez", "firstName": "Jessica", "address": "909 Washington St.", "zipCode": "32519", "phone": "(783) 489 - 2423", "email": "jessica.gonzalez@example.com"}, {"city": "Jacksonville", "state": "FL", "surname": "Torres", "firstName": "Nicole", "address": "475 Eighth Blvd.", "zipCode": "32363", "phone": "(611) 412 - 8933", "email": "nicole.torres@example.com"}, {"city": "Miami", "state": "FL", "surname": "Lopez", "firstName": "Brenda", "address": "689 Fifth Ct.", "zipCode": "32213", "phone": "(383) 999 - 4581", "email": "brenda.lopez@example.com"}, {"city": "Orlando", "state": "FL", "surname": "Griffin", "firstName": "Margaret", "address": "780 Sixth St.", "zipCode": "32575", "phone": "(243) 455 - 4152", "email": "margaret.griffin@example.com"}, {"city": "Gainesville", "state": "FL", "surname": "Robinson", "firstName": "David", "address": "912 Hill Ln.", "zipCode": "32236", "phone": "(126) 545 - 5213", "email": "david.robinson@example.com"}]
